<annotation>
	<folder>JPEGImages</folder>
	<filename>1_136.jpg</filename>
	<path>D:\test\faster-rcnn-pytorch-master\VOCdevkit\VOC2007\JPEGImages\1_136.jpg</path>
	<source>
		<database>Unknown</database>
	</source>
	<size>
		<width>224</width>
		<height>224</height>
		<depth>3</depth>
	</size>
	<segmented>0</segmented>
	<object>
		<name>L3</name>
		<pose>Unspecified</pose>
		<truncated>0</truncated>
		<difficult>0</difficult>
		<bndbox>
			<xmin>117</xmin>
			<ymin>81</ymin>
			<xmax>191</xmax>
			<ymax>158</ymax>
		</bndbox>
	</object>
	<object>
		<name>L4</name>
		<pose>Unspecified</pose>
		<truncated>0</truncated>
		<difficult>0</difficult>
		<bndbox>
			<xmin>33</xmin>
			<ymin>29</ymin>
			<xmax>217</xmax>
			<ymax>217</ymax>
		</bndbox>
	</object>
</annotation>
