<annotation>
	<folder>JPEGImages</folder>
	<filename>1_2088.jpg</filename>
	<path>D:\test\faster-rcnn-pytorch-master\VOCdevkit\VOC2007\JPEGImages\1_2088.jpg</path>
	<source>
		<database>Unknown</database>
	</source>
	<size>
		<width>224</width>
		<height>224</height>
		<depth>3</depth>
	</size>
	<segmented>0</segmented>
	<object>
		<name>L3</name>
		<pose>Unspecified</pose>
		<truncated>0</truncated>
		<difficult>0</difficult>
		<bndbox>
			<xmin>173</xmin>
			<ymin>141</ymin>
			<xmax>205</xmax>
			<ymax>184</ymax>
		</bndbox>
	</object>
	<object>
		<name>L4</name>
		<pose>Unspecified</pose>
		<truncated>0</truncated>
		<difficult>0</difficult>
		<bndbox>
			<xmin>41</xmin>
			<ymin>41</ymin>
			<xmax>204</xmax>
			<ymax>203</ymax>
		</bndbox>
	</object>
</annotation>
